aussiebb/__init__.py
aussiebb/portal.py
aussiebb-0.2.dist-info/LICENSE
aussiebb-0.2.dist-info/METADATA
aussiebb-0.2.dist-info/WHEEL
aussiebb-0.2.dist-info/top_level.txt
aussiebb-0.2.dist-info/RECORD
