Metadata-Version: 2.1
Name: aussiebb
Version: 0.2
Summary: A python library to interact with the Aussie Broadband customer portal
Home-page: https://www.madebymikal.com/aussiebb
Author: Michael Still
Author-email: mikal@stillhq.com
License: UNKNOWN
Platform: UNKNOWN
Classifier: Programming Language :: Python :: 3
Classifier: License :: OSI Approved :: Apache Software License
Classifier: Operating System :: OS Independent
